{
  "year": 1880,
  "page": 118,
  "node_id": "761aa6f5-8caa-43ac-a45b-1d44f314c972",
  "has_markup": true,
  "entries": [
    {
      "bbox": {
        "height": 306,
        "width": 1825,
        "x": 989,
        "y": 1181
      },
      "entry_id": "761aa6f5-8caa-43ac-a45b-1d44f314c972_6",
      "people": [
        {
          "age": "",
          "geo": "",
          "info": "",
          "name": "Анна",
          "second_name": "Максимова",
          "sex": "FEMALE",
          "status": "BORN",
          "surname": ""
        },
        {
          "age": "",
          "geo": "Алексинский уезд, село Волковичье",
          "info": "крестьянин",
          "name": "Тимофей",
          "second_name": "Васильев",
          "sex": "MALE",
          "status": "GODFATHER",
          "surname": ""
        },
        {
          "age": "",
          "geo": "",
          "info": "",
          "name": "Анна",
          "second_name": "Аполлонова",
          "sex": "FEMALE",
          "status": "MOTHER",
          "surname": ""
        },
        {
          "age": "",
          "geo": "сельцо Глазечка",
          "info": "крестьянская девица",
          "name": "Анна",
          "second_name": "Федорова",
          "sex": "FEMALE",
          "status": "GODMOTHER",
          "surname": ""
        },
        {
          "age": "",
          "geo": "сельцо Глазечка",
          "info": "крестьянин",
          "name": "Максим",
          "second_name": "Ермилов",
          "sex": "MALE",
          "status": "FATHER",
          "surname": ""
        }
      ],
      "type": "BIRTH"
    },
    {
      "bbox": {
        "height": 375,
        "width": 1862,
        "x": 1000,
        "y": 1527
      },
      "entry_id": "761aa6f5-8caa-43ac-a45b-1d44f314c972_1",
      "people": [
        {
          "age": "",
          "geo": "",
          "info": "",
          "name": "Мария",
          "second_name": "Алексеева",
          "sex": "FEMALE",
          "status": "BORN",
          "surname": ""
        },
        {
          "age": "",
          "geo": "Тарусский уезд, деревня Барсуково",
          "info": "крестьянская девица",
          "name": "Феодосия",
          "second_name": "Яковлева",
          "sex": "FEMALE",
          "status": "GODMOTHER",
          "surname": ""
        },
        {
          "age": "",
          "geo": "Тульская губерния, Одоевский уезд, сельцо Дроково",
          "info": "крестьянин",
          "name": "Алексей",
          "second_name": "Иванов",
          "sex": "MALE",
          "status": "FATHER",
          "surname": ""
        },
        {
          "age": "",
          "geo": "",
          "info": "",
          "name": "Анна",
          "second_name": "Васильева",
          "sex": "FEMALE",
          "status": "MOTHER",
          "surname": ""
        },
        {
          "age": "",
          "geo": "деревня Заборье",
          "info": "крестьянин",
          "name": "Иван",
          "second_name": "Васильев",
          "sex": "MALE",
          "status": "GODFATHER",
          "surname": ""
        }
      ],
      "type": "BIRTH"
    },
    {
      "bbox": {
        "height": 440,
        "width": 1848,
        "x": 1004,
        "y": 1935
      },
      "entry_id": "761aa6f5-8caa-43ac-a45b-1d44f314c972_3",
      "people": [
        {
          "age": "",
          "geo": "4-й Туркестанский стрелковый батальон",
          "info": "рядовой",
          "name": "Иван",
          "second_name": "Симеонов",
          "sex": "MALE",
          "status": "GODFATHER",
          "surname": ""
        },
        {
          "age": "",
          "geo": "сельцо Злобино",
          "info": "крестьянская девица",
          "name": "Агрипина",
          "second_name": "Александрова",
          "sex": "FEMALE",
          "status": "GODMOTHER",
          "surname": ""
        },
        {
          "age": "",
          "geo": "",
          "info": "",
          "name": "Надежда",
          "second_name": "Павлова",
          "sex": "FEMALE",
          "status": "MOTHER",
          "surname": ""
        },
        {
          "age": "",
          "geo": "",
          "info": "",
          "name": "Мария",
          "second_name": "Филиппова",
          "sex": "FEMALE",
          "status": "BORN",
          "surname": ""
        },
        {
          "age": "",
          "geo": "Тульская губерния, Алексинский уезд, Липицкая волость, село Покровское",
          "info": "крестьянин",
          "name": "Филипп",
          "second_name": "Васильев",
          "sex": "MALE",
          "status": "FATHER",
          "surname": ""
        }
      ],
      "type": "BIRTH"
    },
    {
      "bbox": {
        "height": 354,
        "width": 1858,
        "x": 1016,
        "y": 2453
      },
      "entry_id": "761aa6f5-8caa-43ac-a45b-1d44f314c972_5",
      "people": [
        {
          "age": "",
          "geo": "",
          "info": "24-й пехотный Симбирский полк рядовой",
          "name": "Алексей",
          "second_name": "Иванов",
          "sex": "MALE",
          "status": "FATHER",
          "surname": ""
        },
        {
          "age": "",
          "geo": "",
          "info": "",
          "name": "Матрона",
          "second_name": "Флорова",
          "sex": "FEMALE",
          "status": "MOTHER",
          "surname": ""
        },
        {
          "age": "",
          "geo": "деревня Иваньково",
          "info": "крестьянская девица",
          "name": "Мария",
          "second_name": "Феодорова",
          "sex": "FEMALE",
          "status": "GODMOTHER",
          "surname": ""
        },
        {
          "age": "",
          "geo": "деревня Иваньково",
          "info": "веневский мещанин",
          "name": "Николай",
          "second_name": "Александров",
          "sex": "MALE",
          "status": "GODFATHER",
          "surname": "Брежнев"
        },
        {
          "age": "",
          "geo": "",
          "info": "",
          "name": "Мария",
          "second_name": "Алексеева",
          "sex": "FEMALE",
          "status": "BORN",
          "surname": ""
        }
      ],
      "type": "BIRTH"
    },
    {
      "bbox": {
        "height": 363,
        "width": 1862,
        "x": 1013,
        "y": 2848
      },
      "entry_id": "761aa6f5-8caa-43ac-a45b-1d44f314c972_4",
      "people": [
        {
          "age": "",
          "geo": "",
          "info": "",
          "name": "Анна",
          "second_name": "Иванова",
          "sex": "FEMALE",
          "status": "GODMOTHER",
          "surname": ""
        },
        {
          "age": "",
          "geo": "",
          "info": "",
          "name": "Софья",
          "second_name": "Леонтьева",
          "sex": "FEMALE",
          "status": "MOTHER",
          "surname": ""
        },
        {
          "age": "",
          "geo": "Серпухов",
          "info": "мещанин",
          "name": "Владимир",
          "other_status": "муж крестной матери",
          "second_name": "Рудольфов",
          "sex": "MALE",
          "status": "OTHER",
          "surname": ""
        },
        {
          "age": "",
          "geo": "",
          "info": "",
          "name": "Мария",
          "second_name": "Васильева",
          "sex": "FEMALE",
          "status": "BORN",
          "surname": ""
        },
        {
          "age": "",
          "geo": "сельцо Дроково",
          "info": "крестьянин",
          "name": "Матвей",
          "second_name": "Никитин",
          "sex": "MALE",
          "status": "GODFATHER",
          "surname": ""
        },
        {
          "age": "",
          "geo": "",
          "info": "серпуховской мещанин",
          "name": "Василий",
          "second_name": "Иванов",
          "sex": "MALE",
          "status": "FATHER",
          "surname": ""
        }
      ],
      "type": "BIRTH"
    },
    {
      "bbox": {
        "height": 458,
        "width": 1849,
        "x": 1023,
        "y": 3248
      },
      "entry_id": "761aa6f5-8caa-43ac-a45b-1d44f314c972_0",
      "people": [
        {
          "age": "",
          "geo": "",
          "info": "",
          "name": "Марина",
          "second_name": "Евдокимова",
          "sex": "FEMALE",
          "status": "MOTHER",
          "surname": ""
        },
        {
          "age": "",
          "geo": "",
          "info": "",
          "name": "Мария",
          "second_name": "Димитриева",
          "sex": "FEMALE",
          "status": "BORN",
          "surname": ""
        },
        {
          "age": "",
          "geo": "Новгородский полк",
          "info": "рядовой",
          "name": "Никанор",
          "second_name": "Спиридонов",
          "sex": "MALE",
          "status": "GODFATHER",
          "surname": ""
        },
        {
          "age": "",
          "geo": "Тарусский уезд, Исканская волость, село Знаменское",
          "info": "крестьянин",
          "name": "Димитрий",
          "second_name": "Афонасьев",
          "sex": "MALE",
          "status": "FATHER",
          "surname": ""
        },
        {
          "age": "",
          "geo": "деревня Покуснево",
          "info": "крестьянская девица",
          "name": "Ирина",
          "second_name": "Иларионова",
          "sex": "FEMALE",
          "status": "GODMOTHER",
          "surname": "Ковалева"
        }
      ],
      "type": "BIRTH"
    },
    {
      "bbox": {
        "height": 482,
        "width": 1903,
        "x": 1032,
        "y": 3751
      },
      "entry_id": "761aa6f5-8caa-43ac-a45b-1d44f314c972_2",
      "people": [
        {
          "age": "",
          "geo": "Алексинская волость, деревня Лисенки",
          "info": "крестьянин",
          "name": "Егор",
          "second_name": "Родионов",
          "sex": "MALE",
          "status": "FATHER",
          "surname": ""
        },
        {
          "age": "",
          "geo": "Алексинский уезд, Темьяновская волость, село Бехово",
          "info": "крестьянин",
          "name": "Николай",
          "second_name": "Иванов",
          "sex": "MALE",
          "status": "GODFATHER",
          "surname": ""
        },
        {
          "age": "",
          "geo": "",
          "info": "",
          "name": "Анастасия",
          "second_name": "Никитина",
          "sex": "FEMALE",
          "status": "MOTHER",
          "surname": ""
        },
        {
          "age": "",
          "geo": "",
          "info": "",
          "name": "Феодор",
          "second_name": "Егоров",
          "sex": "MALE",
          "status": "BORN",
          "surname": ""
        }
      ],
      "type": "BIRTH"
    }
  ]
}