{
  "year": 1914,
  "page": 174,
  "node_id": "ea8c331f-a704-4670-9a3d-303b1ccba44e",
  "has_markup": true,
  "entries": [
    {
      "bbox": {
        "height": 966,
        "width": 3413,
        "x": 619,
        "y": 943
      },
      "entry_id": "ea8c331f-a704-4670-9a3d-303b1ccba44e_1",
      "people": [
        {
          "age": "",
          "geo": "Московская губерния, Семеновская слобода",
          "info": "мещанин",
          "name": "Гаврил",
          "second_name": "Гаврилов",
          "sex": "MALE",
          "status": "WITNESS",
          "surname": ""
        },
        {
          "age": "",
          "geo": "Московская губерния, Семеновская слобода",
          "info": "мещанин",
          "name": "Гаврил",
          "second_name": "Емельянов",
          "sex": "MALE",
          "status": "WITNESS",
          "surname": ""
        },
        {
          "age": "32",
          "geo": "",
          "info": "орловская мещанка, девица",
          "name": "Параскева",
          "second_name": "Петрова",
          "sex": "FEMALE",
          "status": "BRIDE",
          "surname": "Волкова"
        },
        {
          "age": "31",
          "geo": "Лифляндская губерния, Феллинский уезд, Тайверская волость",
          "info": "крестьянин",
          "name": "Иоганн-Карл",
          "second_name": "Юрьев",
          "sex": "MALE",
          "status": "GROOM",
          "surname": "Якобсон"
        },
        {
          "age": "",
          "geo": "Минская губерния, Острошицко-Городецкая волость, деревня Королева Стана",
          "info": "крестьянин",
          "name": "Степан",
          "second_name": "Осипов",
          "sex": "MALE",
          "status": "WITNESS",
          "surname": "Канаревский"
        },
        {
          "age": "",
          "geo": "Тверская губерния, Калязинский уезд, Степановская волость, деревня Ново-Акатово",
          "info": "крестьянин",
          "name": "Никита",
          "second_name": "Семенов",
          "sex": "MALE",
          "status": "WITNESS",
          "surname": "Воронов"
        }
      ],
      "type": "WEDDING"
    },
    {
      "bbox": {
        "height": 1116,
        "width": 3475,
        "x": 603,
        "y": 2077
      },
      "entry_id": "ea8c331f-a704-4670-9a3d-303b1ccba44e_0",
      "people": [
        {
          "age": "",
          "geo": "Московская губерния, Клинский уезд, Борщевская волость, село Красное",
          "info": "крестьянин",
          "name": "Павел",
          "second_name": "Никитин",
          "sex": "MALE",
          "status": "WITNESS",
          "surname": "Скрипкин"
        },
        {
          "age": "",
          "geo": "Тверская губерния, Ржевский уезд, Тереховская волость, деревня Буболевка",
          "info": "крестьянин",
          "name": "Иван",
          "second_name": "Космин",
          "sex": "MALE",
          "status": "WITNESS",
          "surname": "Матвеев"
        },
        {
          "age": "",
          "geo": "Симбирская губерния, Курмышский уезд, Знаменская волость, село Княжья Гора",
          "info": "крестьянин",
          "name": "Иван",
          "second_name": "Васильев",
          "sex": "MALE",
          "status": "WITNESS",
          "surname": "Никифоров"
        },
        {
          "age": "",
          "geo": "то же село",
          "info": "крестьянин",
          "name": "Прокопий",
          "second_name": "Николаев",
          "sex": "MALE",
          "status": "WITNESS",
          "surname": "Ерохин"
        },
        {
          "age": "23",
          "geo": "Тульская губерния, Крапивинский уезд, Красногорская волость, село Лесок",
          "info": "девица",
          "name": "Анна",
          "second_name": "Фомина",
          "sex": "FEMALE",
          "status": "BRIDE",
          "surname": "Кузнецова (Чупикина)"
        },
        {
          "age": "25",
          "geo": "Московская губерния, Звенигородский уезд, Перхушковская волость, село Акулово",
          "info": "крестьянин",
          "name": "Иван",
          "second_name": "Дмитриев",
          "sex": "MALE",
          "status": "GROOM",
          "surname": "Кузнецов"
        }
      ],
      "type": "WEDDING"
    }
  ],
  "total_pages": null
}